lccs/__init__.py
lccs/__init__.pyi
lccs/classes.py
lccs/classes.pyi
lccs/classification_system.py
lccs/classification_system.pyi
lccs/cli.py
lccs/cli.pyi
lccs/lccs.py
lccs/lccs.pyi
lccs/link.py
lccs/link.pyi
lccs/mappings.py
lccs/mappings.pyi
lccs/style_formats.py
lccs/style_formats.pyi
lccs/style_utils.py
lccs/style_utils.pyi
lccs/utils.py
lccs/utils.pyi
lccs/version.py
lccs/version.pyi
lccs/jsonschemas/classification_systems.json
lccs/templates/classification_system.html
lccs/templates/classification_systems.html
lccs/templates/mapping-item.html
lccs/templates/mapping.html
lccs-1.0.2.dist-info/METADATA
lccs-1.0.2.dist-info/WHEEL
lccs-1.0.2.dist-info/entry_points.txt
lccs-1.0.2.dist-info/top_level.txt
lccs-1.0.2.dist-info/RECORD
